{
    "problem_id": "105",
    "initial_string": "aaab",
    "transitions": [
        {
            "src": "a",
            "tgt": "abc"
        },
        {
            "src": "aabcbdcb",
            "tgt": "aabbbc"
        },
        {
            "src": "a",
            "tgt": "ab"
        },
        {
            "src": "ababacbc",
            "tgt": "a"
        },
        {
            "src": "abcdedcf",
            "tgt": "aaaab"
        },
        {
            "src": "abbcbcaab",
            "tgt": ""
        }
    ]
}