{
    "problem_id": "096",
    "initial_string": "ab",
    "transitions": [
        {
            "src": "aaa",
            "tgt": "a"
        },
        {
            "src": "a",
            "tgt": "aa"
        },
        {
            "src": "aa",
            "tgt": ""
        },
        {
            "src": "a",
            "tgt": ""
        },
        {
            "src": "a",
            "tgt": "aa"
        },
        {
            "src": "",
            "tgt": ""
        }
    ],
    "markov_entropy": 1.0,
    "pattern_score": 0.36907024642854247
}