{
    "problem_id": "153",
    "initial_string": "aab",
    "transitions": [
        {
            "src": "baabba",
            "tgt": ""
        },
        {
            "src": "bbb",
            "tgt": "a"
        },
        {
            "src": "a",
            "tgt": "abaaba"
        },
        {
            "src": "a",
            "tgt": "b"
        },
        {
            "src": "a",
            "tgt": "bab"
        },
        {
            "src": "bbbbabaababaaba",
            "tgt": ""
        }
    ],
    "markov_entropy": 2.0,
    "pattern_score": 0.1386468838532139
}