{
    "problem_id": "099",
    "initial_string": "abac",
    "transitions": [
        {
            "src": "bacaaaab",
            "tgt": "d"
        },
        {
            "src": "b",
            "tgt": "acdc"
        },
        {
            "src": "a",
            "tgt": "deecbbda"
        },
        {
            "src": "b",
            "tgt": "ceaacda"
        },
        {
            "src": "deeccedeecbbdaacdaceaacdadaceaacdaac",
            "tgt": ""
        }
    ],
    "markov_entropy": 1.9219280948873623,
    "pattern_score": 0.2564967211898894
}