{
    "problem_id": "538",
    "initial_string": "abcdd",
    "transitions": [
        {
            "src": "b",
            "tgt": "feefeaeba"
        },
        {
            "src": "acbaddbc",
            "tgt": "b"
        },
        {
            "src": "c",
            "tgt": "ceecef"
        },
        {
            "src": "c",
            "tgt": "efcef"
        },
        {
            "src": "afeefeaebaefefefcefeecefefefdd",
            "tgt": ""
        }
    ],
    "markov_entropy": 2.321928094887362,
    "pattern_score": 0.10175559829607284
}