{
    "problem_id": "721",
    "initial_string": "aabba",
    "transitions": [
        {
            "src": "bba",
            "tgt": "d"
        },
        {
            "src": "b",
            "tgt": "abbacb"
        },
        {
            "src": "a",
            "tgt": "cc"
        },
        {
            "src": "bbbbb",
            "tgt": "caccadcda"
        },
        {
            "src": "ccccaabbacbbacbba",
            "tgt": ""
        }
    ],
    "markov_entropy": 2.0,
    "pattern_score": 0.1386468838532139
}