{
    "problem_id": "096",
    "initial_string": "abbcc",
    "transitions": [
        {
            "src": "IfaaSt_p/d",
            "tgt": "N_pak/IIaS"
        },
        {
            "src": ".dS",
            "tgt": "bdt_b.fIS."
        },
        {
            "src": "SSpaN.lkd",
            "tgt": "ftlIfd.kp"
        },
        {
            "src": "_",
            "tgt": "ppl"
        },
        {
            "src": "tdaakfIpbI",
            "tgt": "NNaN"
        },
        {
            "src": "abbcc",
            "tgt": ""
        }
    ],
    "markov_entropy": 0.0,
    "pattern_score": 1
}