{
    "problem_id": "166",
    "initial_string": "abcdbdcdd",
    "transitions": [
        {
            "src": "d",
            "tgt": "ebbd"
        },
        {
            "src": "abcbbdadda",
            "tgt": "cdc"
        },
        {
            "src": "dabbdd",
            "tgt": "dccbed"
        },
        {
            "src": "d",
            "tgt": "a"
        },
        {
            "src": "ba",
            "tgt": "abefbbfee"
        },
        {
            "src": "abcebbebbebbebbebbebbeabefbbfeebefbbfeeabefbbfeecebabefbbfeea",
            "tgt": ""
        }
    ],
    "markov_entropy": 2.7806390622295662,
    "pattern_score": 0.31971514599042095
}