{
    "problem_id": "339",
    "initial_string": "aa",
    "transitions": [
        {
            "src": "a",
            "tgt": "ba"
        },
        {
            "src": "aaaa",
            "tgt": "ccac"
        },
        {
            "src": "a",
            "tgt": "aab"
        },
        {
            "src": "a",
            "tgt": "b"
        },
        {
            "src": "a",
            "tgt": "cacc"
        },
        {
            "src": "a",
            "tgt": "bbba"
        },
        {
            "src": "bbbbbbbbbccaabccababccbbaba",
            "tgt": ""
        }
    ],
    "markov_entropy": 3.3927474104487847,
    "pattern_score": 0.10889647014698423
}