{
    "problem_id": "433",
    "initial_string": "abbccba",
    "transitions": [
        {
            "src": "a",
            "tgt": "aeceaadcdd"
        },
        {
            "src": "acc",
            "tgt": "bec"
        },
        {
            "src": "aacbbccbab",
            "tgt": "aae"
        },
        {
            "src": "acbbcabcbc",
            "tgt": "eebbbeaee"
        },
        {
            "src": "a",
            "tgt": "ceedc"
        },
        {
            "src": "c",
            "tgt": "bcaee"
        },
        {
            "src": "bbcceedceeceedcececeedcceedceceaeceaadcddadcddeceaadcdddcddeceaadcddeeeedcbbccbceedc",
            "tgt": ""
        }
    ],
    "markov_entropy": 3.0269868333592873,
    "pattern_score": 0.20496331565447634
}