{
    "problem_id": "619",
    "initial_string": "abacd",
    "transitions": [
        {
            "src": "caccdddacc",
            "tgt": "b"
        },
        {
            "src": "accadaac",
            "tgt": "b"
        },
        {
            "src": "a",
            "tgt": "aeda"
        },
        {
            "src": "ddbbbad",
            "tgt": "dc"
        },
        {
            "src": "aedaedaedaedaedaedaedaedaedaedabacd",
            "tgt": ""
        }
    ],
    "markov_entropy": 0.4689955935892812,
    "pattern_score": 0.8644298701952597
}