{
    "problem_id": "864",
    "initial_string": "abcdebcc",
    "transitions": [
        {
            "src": "b",
            "tgt": ""
        },
        {
            "src": "IN",
            "tgt": ""
        },
        {
            "src": "lf/a./dtNk",
            "tgt": "l"
        },
        {
            "src": "lN.IkbS",
            "tgt": ""
        },
        {
            "src": "SNN",
            "tgt": "tbkI"
        },
        {
            "src": "k/INt",
            "tgt": "_dt/IkpakN"
        },
        {
            "src": "acdebcc",
            "tgt": ""
        }
    ],
    "markov_entropy": 0.0,
    "pattern_score": 1.0
}