{
    "problem_id": "878",
    "initial_string": "abcdcda",
    "transitions": [
        {
            "src": "bcdddbdc",
            "tgt": "fcdbdba"
        },
        {
            "src": "bcdc",
            "tgt": "c"
        },
        {
            "src": "abbadcd",
            "tgt": "bfe"
        },
        {
            "src": "d",
            "tgt": "baefcd"
        },
        {
            "src": "bdcabcdcd",
            "tgt": "cbcfaeae"
        },
        {
            "src": "ddc",
            "tgt": "aeafff"
        },
        {
            "src": "abcbaefcbaefcbaefcbaefcbaefcbaefcbaefcbaefcbaefcbaefcbaefcbaefcbaefcbaefcbaefcdcda",
            "tgt": ""
        }
    ],
    "markov_entropy": 0.35335933502142136,
    "pattern_score": 0.9116601662446446
}