{
    "problem_id": "879",
    "initial_string": "ab",
    "transitions": [
        {
            "src": "aaa",
            "tgt": "b"
        },
        {
            "src": "b",
            "tgt": "ca"
        },
        {
            "src": "a",
            "tgt": "db"
        },
        {
            "src": "bb",
            "tgt": "b"
        },
        {
            "src": "dcdcdbcdcdcdb",
            "tgt": ""
        }
    ],
    "markov_entropy": 2.2312702546075758,
    "pattern_score": 0.37760290263601637
}