{
    "problem_id": "290",
    "initial_string": "abbcd",
    "transitions": [
        {
            "src": "ba",
            "tgt": "baabababbb"
        },
        {
            "src": "b",
            "tgt": "a"
        },
        {
            "src": "b",
            "tgt": "bbb"
        },
        {
            "src": "b",
            "tgt": ""
        },
        {
            "src": "bba",
            "tgt": "bb"
        },
        {
            "src": "a",
            "tgt": "bba"
        },
        {
            "src": "aabbbbaabababbbbaabababbbabababbbabababbbbb",
            "tgt": ""
        }
    ],
    "markov_entropy": 2.725480556997868,
    "pattern_score": 0.17954859974466675
}